Text_Converter/__init__.py
Text_Converter-1.0.1.dist-info/DESCRIPTION.rst
Text_Converter-1.0.1.dist-info/METADATA
Text_Converter-1.0.1.dist-info/RECORD
Text_Converter-1.0.1.dist-info/WHEEL
Text_Converter-1.0.1.dist-info/metadata.json
Text_Converter-1.0.1.dist-info/top_level.txt
