Metadata-Version: 2.0
Name: Text-Converter
Version: 1.0.1
Summary: A Python package to Calculate Conventions
Home-page: https://github.com/OMoF/Converter
Author: Omar Faruk
Author-email: omfaruk.om@gmail.com
License: MIT
Platform: UNKNOWN
Classifier: License :: OSI Approved :: MIT License
Classifier: Programming Language :: Python :: 3
Classifier: Programming Language :: Python :: 3.7
